MANIFEST.in
README.rst
setup.py
my_test_package/__init__.py
my_test_package/mymodule.py
my_test_package.egg-info/PKG-INFO
my_test_package.egg-info/SOURCES.txt
my_test_package.egg-info/dependency_links.txt
my_test_package.egg-info/entry_points.txt
my_test_package.egg-info/not-zip-safe
my_test_package.egg-info/top_level.txt