Metadata-Version: 1.1
Name: my-test-package
Version: 0.1.1
Summary: A simple test program to investigate packaging and PyPI
Home-page: https://github.com/aeraquoo/my_test_package
Author: Jaye Heffernan
Author-email: jayejaye@live.com.au
License: MIT
Platform: UNKNOWN
Classifier: Programming Language :: Python :: 2.7
Classifier: Programming Language :: Python :: 3.5
